nonebot_plugin_jtj/__init__.py
nonebot_plugin_jtj-0.2.1.dist-info/LICENSE
nonebot_plugin_jtj-0.2.1.dist-info/METADATA
nonebot_plugin_jtj-0.2.1.dist-info/WHEEL
nonebot_plugin_jtj-0.2.1.dist-info/top_level.txt
nonebot_plugin_jtj-0.2.1.dist-info/RECORD
