Metadata-Version: 2.1
Name: nonebot-plugin-jtj
Version: 0.2.1
Summary: 本地机厅管理人数上报的 NoneBot 插件
Author: QiYork
Author-email: 1309946582@qq.com
Project-URL: Homepage, https://github.com/Onimaimai/nonebot-plugin-jtj
Classifier: Programming Language :: Python :: 3
Classifier: License :: OSI Approved :: MIT License
Classifier: Operating System :: OS Independent
Requires-Python: >=3.9
License-File: LICENSE
Requires-Dist: nonebot2 >=2.2.0
Requires-Dist: nonebot-adapter-onebot >=2.1.5
Requires-Dist: nonebot-plugin-apscheduler
Requires-Dist: nonebot-plugin-localstore
